CONTRIBUTORS.txt
MANIFEST.in
README.md
setup.py
docs/HISTORY.txt
docs/INSTALL.txt
docs/LICENSE.GPL
docs/LICENSE.txt
redturtle/__init__.py
redturtle.portlets.inspector.egg-info/PKG-INFO
redturtle.portlets.inspector.egg-info/SOURCES.txt
redturtle.portlets.inspector.egg-info/dependency_links.txt
redturtle.portlets.inspector.egg-info/entry_points.txt
redturtle.portlets.inspector.egg-info/namespace_packages.txt
redturtle.portlets.inspector.egg-info/not-zip-safe
redturtle.portlets.inspector.egg-info/requires.txt
redturtle.portlets.inspector.egg-info/top_level.txt
redturtle/portlets/__init__.py
redturtle/portlets/inspector/README.txt
redturtle/portlets/inspector/__init__.py
redturtle/portlets/inspector/config.py
redturtle/portlets/inspector/configure.zcml
redturtle/portlets/inspector/browser/__init__.py
redturtle/portlets/inspector/browser/configure.zcml
redturtle/portlets/inspector/browser/inspector.py
redturtle/portlets/inspector/tests/__init__.py
redturtle/portlets/inspector/tests/base.py
redturtle/portlets/inspector/tests/test_doctest.py